sqlalchemy_fake_model/ModelFaker.py
sqlalchemy_fake_model/__init__.py
sqlalchemy_fake_model/Enum/ModelColumnTypesEnum.py
sqlalchemy_fake_model/Enum/ModelRelationTypesEnum.py
sqlalchemy_fake_model/Enum/__init__.py
sqlalchemy_fake_model-0.0.0.dist-info/LICENSE
sqlalchemy_fake_model-0.0.0.dist-info/METADATA
sqlalchemy_fake_model-0.0.0.dist-info/WHEEL
sqlalchemy_fake_model-0.0.0.dist-info/top_level.txt
sqlalchemy_fake_model-0.0.0.dist-info/RECORD
