Metadata-Version: 2.1
Name: sqlalchemy-fake-model
Version: 0.0.0
Summary: A library to generate complex fake database-entries based on SQLAlchemy models
Home-page: https://github.com/LeanderCS/sqlalchemy-fake-model
Author: Leander Cain Slotosch
Author-email: slotosch.leander@outlook.de
License: UNKNOWN
Project-URL: Documentation, https://leandercs.github.io/sqlalchemy-fake-model
Project-URL: Source, https://github.com/LeanderCS/sqlalchemy-fake-model
Platform: UNKNOWN
Classifier: License :: OSI Approved :: MIT License
Classifier: Operating System :: OS Independent
Classifier: Programming Language :: Python :: 3.13
Classifier: Programming Language :: Python :: 3.12
Classifier: Programming Language :: Python :: 3.11
Classifier: Programming Language :: Python :: 3.10
Classifier: Programming Language :: Python :: 3.9
Classifier: Programming Language :: Python :: 3.8
Classifier: Programming Language :: Python :: 3.7
Classifier: Programming Language :: Python :: 3.6
Requires-Python: >=3.6
License-File: LICENSE
Requires-Dist: SQLAlchemy>=1.3
Requires-Dist: Faker>=2.0.0
